joblib_progress/__init__.py
joblib_progress/py.typed
joblib_progress-1.0.6.dist-info/LICENSE
joblib_progress-1.0.6.dist-info/METADATA
joblib_progress-1.0.6.dist-info/WHEEL
joblib_progress-1.0.6.dist-info/top_level.txt
joblib_progress-1.0.6.dist-info/RECORD
