Metadata-Version: 2.1
Name: joblib-progress
Version: 1.0.6
Summary: A contextmanager to track progress of joblib execution
Home-page: https://github.com/jonghwanhyeon/joblib-progress
Author: Jonghwan Hyeon
Author-email: jonghwanhyeon93@gmail.com
License: MIT
Keywords: joblib,progress,rich
Classifier: Development Status :: 4 - Beta
Classifier: License :: OSI Approved :: MIT License
Classifier: Programming Language :: Python :: 3
Classifier: Programming Language :: Python :: 3 :: Only
Requires-Python: >=3.7
License-File: LICENSE
Requires-Dist: joblib
Requires-Dist: rich
